pyseismic/__init__.py
pyseismic/colormap.py
pyseismic/data_processing.py
pyseismic/image_processing.py
pyseismic-0.0.6.dist-info/LICENSE
pyseismic-0.0.6.dist-info/METADATA
pyseismic-0.0.6.dist-info/WHEEL
pyseismic-0.0.6.dist-info/top_level.txt
pyseismic-0.0.6.dist-info/RECORD
