Metadata-Version: 2.1
Name: pyseismic
Version: 0.0.6
Summary: A package for seismic data processing
Home-page: https://github.com/XintaoChai
Author: Xintao Chai
Author-email: xtchai@126.com
Classifier: Programming Language :: Python :: 3
Classifier: License :: OSI Approved :: MIT License
Classifier: Operating System :: OS Independent
License-File: LICENSE
